adamlint-1.1.0.dist-info/licenses/LICENSE
zulint/__init__.py
zulint/command.py
zulint/custom_rules.py
zulint/linters.py
zulint/lister.py
zulint/printer.py
zulint/py.typed
adamlint-1.1.0.dist-info/METADATA
adamlint-1.1.0.dist-info/WHEEL
adamlint-1.1.0.dist-info/top_level.txt
adamlint-1.1.0.dist-info/RECORD
